pytorch_vision_classifier/lr_finder.py
pytorch_vision_classifier/pytorch_data_transformation.py
pytorch_vision_classifier/pytorch_dataset_preparation.py
pytorch_vision_classifier/pytorch_dataset_samplers.py
pytorch_vision_classifier/pytorch_device_manager.py
pytorch_vision_classifier/pytorch_loss_function.py
pytorch_vision_classifier/pytorch_model_training.py
pytorch_vision_classifier/utilities.py
pytorch_vision_classifier-0.0.10.dist-info/LICENSE
pytorch_vision_classifier-0.0.10.dist-info/METADATA
pytorch_vision_classifier-0.0.10.dist-info/WHEEL
pytorch_vision_classifier-0.0.10.dist-info/top_level.txt
pytorch_vision_classifier-0.0.10.dist-info/RECORD
