Metadata-Version: 2.1
Name: pytorch-vision-classifier
Version: 0.0.10
Summary: This library is to help you train and evaluate PyTorch classification model easily and quickly
Home-page: https://github.com/Samer92/pytorch_vision_classifier
Author: sammer sallam
Author-email: samersallam92@gmail.com
License: UNKNOWN
Platform: UNKNOWN
Classifier: Programming Language :: Python :: 3
Classifier: License :: OSI Approved :: MIT License
Classifier: Operating System :: OS Independent
Requires-Python: >=3.6
Requires-Dist: backcall (==0.2.0)
Requires-Dist: classification-analysis (==0.0.2)
Requires-Dist: colorama (==0.4.3)
Requires-Dist: cycler (==0.10.0)
Requires-Dist: decorator (==4.4.2)
Requires-Dist: imbalanced-learn (==0.7.0)
Requires-Dist: imblearn (==0.0)
Requires-Dist: ipython (==7.16.1)
Requires-Dist: ipython-genutils (==0.2.0)
Requires-Dist: jedi (==0.17.1)
Requires-Dist: joblib (==0.15.1)
Requires-Dist: kiwisolver (==1.2.0)
Requires-Dist: matplotlib (==3.2.2)
Requires-Dist: numpy (==1.19.0)
Requires-Dist: opencv-python (==4.2.0.34)
Requires-Dist: pandas (==1.0.5)
Requires-Dist: parso (==0.7.0)
Requires-Dist: pickleshare (==0.7.5)
Requires-Dist: Pillow (==7.1.2)
Requires-Dist: prompt-toolkit (==3.0.5)
Requires-Dist: Pygments (==2.6.1)
Requires-Dist: pyparsing (==2.4.7)
Requires-Dist: python-dateutil (==2.8.1)
Requires-Dist: pytz (==2020.1)
Requires-Dist: scikit-learn (==0.23.1)
Requires-Dist: scipy (==1.5.0)
Requires-Dist: seaborn (==0.10.1)
Requires-Dist: six (==1.15.0)
Requires-Dist: threadpoolctl (==2.1.0)
Requires-Dist: tqdm (==4.46.1)
Requires-Dist: traitlets (==4.3.3)
Requires-Dist: wcwidth (==0.2.5)
